mockingjay-0.2.0.dist-info/DESCRIPTION.rst
mockingjay-0.2.0.dist-info/top_level.txt
mockingjay-0.2.0.dist-info/WHEEL
mockingjay-0.2.0.dist-info/METADATA
mockingjay-0.2.0.dist-info/metadata.json
mockingjay-0.2.0.dist-info/RECORD
mockingjay/builder.py
mockingjay/__init__.py
mockingjay/service.py
mockingjay/fixture_loader.py
mockingjay/matcher.py
