Metadata-Version: 2.0
Name: mockingjay
Version: 0.2.0
Summary: A simple library to build mock http services based on HTTPretty
Home-page: https://github.com/kevinjqiu/mockingjay
Author: Kevin J. Qiu
Author-email: kevin@idempotent.ca
License: BSD
Keywords: mockingjay
Platform: UNKNOWN
Classifier: Development Status :: 2 - Pre-Alpha
Classifier: Intended Audience :: Developers
Classifier: License :: OSI Approved :: BSD License
Classifier: Natural Language :: English
Classifier: Programming Language :: Python :: 2
Classifier: Programming Language :: Python :: 2.6
Classifier: Programming Language :: Python :: 2.7
Requires-Dist: wheel (==0.23.0)
Requires-Dist: httpretty
Requires-Dist: jinja2
